interpogate.py
proto/__init__.py
proto/__init__.pyi
proto/interpogate_pb2.py
proto/interpogate_pb2.pyi
proto/interpogate_pb2_grpc.py
static/__init__.py
static/index.html
interpogate-0.0.6.dist-info/METADATA
interpogate-0.0.6.dist-info/WHEEL
interpogate-0.0.6.dist-info/top_level.txt
interpogate-0.0.6.dist-info/RECORD
