Metadata-Version: 2.1
Name: interpogate
Version: 0.0.6
Summary: A tool to interpret machine learning models
Author-email: Dylan Freedman <freedmand@gmail.com>
Project-URL: Homepage, https://github.com/freedmand/interpogate
Project-URL: Repository, https://github.com/freedmand/interpogate
Project-URL: Bug Tracker, https://github.com/freedmand/interpogate/issues
Classifier: Programming Language :: Python :: 3
Classifier: License :: OSI Approved :: MIT License
Classifier: Operating System :: OS Independent
Requires-Dist: torch >=2
Requires-Dist: transformers >=4
Requires-Dist: numpy >=1
Requires-Dist: protobuf >=3
Provides-Extra: server
Requires-Dist: grpcio >=1 ; extra == 'server'
